awshttp/__init__.py
awshttp/awshttp.py
awshttp/py.typed
awshttp-0.1.2.dist-info/licenses/LICENSE
awshttp-0.1.2.dist-info/METADATA
awshttp-0.1.2.dist-info/WHEEL
awshttp-0.1.2.dist-info/top_level.txt
awshttp-0.1.2.dist-info/RECORD
