Metadata-Version: 2.4
Name: awshttp
Version: 0.1.2
Summary: Minimal AWS SigV4 signed HTTP requests library
Author: Sam Fakhreddine
License: MIT
Project-URL: Homepage, https://github.com/sam-fakhreddine/awshttp
Project-URL: Repository, https://github.com/sam-fakhreddine/awshttp
Project-URL: Issues, https://github.com/sam-fakhreddine/awshttp/issues
Keywords: aws,sigv4,http,requests,lambda,api-gateway
Classifier: Development Status :: 4 - Beta
Classifier: Intended Audience :: Developers
Classifier: License :: OSI Approved :: MIT License
Classifier: Operating System :: OS Independent
Classifier: Programming Language :: Python :: 3
Classifier: Programming Language :: Python :: 3.10
Classifier: Programming Language :: Python :: 3.11
Classifier: Programming Language :: Python :: 3.12
Classifier: Topic :: Software Development :: Libraries :: Python Modules
Requires-Python: >=3.10
License-File: LICENSE
Requires-Dist: boto3>=1.26.0
Requires-Dist: requests>=2.28.0
Provides-Extra: dev
Requires-Dist: pytest>=7.0.0; extra == "dev"
Requires-Dist: build>=0.10.0; extra == "dev"
Requires-Dist: twine>=4.0.0; extra == "dev"
Dynamic: license-file
